django_kss/__init__.py
django_kss/admin.py
django_kss/models.py
django_kss/setup.py
django_kss/tests.py
django_kss/urls.py
django_kss/views.py
django_kss/static/css/bootstrap-kss-theme.min.css
django_kss/static/css/bootstrap-kss.min.css
django_kss/static/css/buttons.css
django_kss/static/css/forms.css
django_kss/static/css/layout.css
django_kss/static/css/prism.css
django_kss/static/js/bootstrap-kss.min.js
django_kss/static/js/jquery-2.1.1.min.js
django_kss/static/js/prism.js
django_kss/templates/styleguide.html
django_kss/templates/pykss/styleguideblock.html
django_kss/templatetags/__init__.py
django_kss/templatetags/kss_extra.py
django_kss-0.1.8.dist-info/DESCRIPTION.rst
django_kss-0.1.8.dist-info/METADATA
django_kss-0.1.8.dist-info/RECORD
django_kss-0.1.8.dist-info/WHEEL
django_kss-0.1.8.dist-info/metadata.json
django_kss-0.1.8.dist-info/top_level.txt
