Metadata-Version: 2.0
Name: django-kss
Version: 0.1.8
Summary: A simple Django app to make styleguide
Home-page: https://github.com/timtan/django_kss
Author: Tim Hsu
Author-email: tim.yellow@gmail.com
License: BSD License
Platform: UNKNOWN
Classifier: Environment :: Web Environment
Classifier: Framework :: Django
Classifier: Intended Audience :: Developers
Classifier: License :: OSI Approved :: BSD License
Classifier: Operating System :: OS Independent
Classifier: Programming Language :: Python
Classifier: Topic :: Internet :: WWW/HTTP
Classifier: Topic :: Internet :: WWW/HTTP :: Dynamic Content
Requires-Dist: pykss
Requires-Dist: Pygments
